bpcli/__init__.py
bpcli/bpcli.py
bpcli-0.3.0.dist-info/LICENSE
bpcli-0.3.0.dist-info/METADATA
bpcli-0.3.0.dist-info/WHEEL
bpcli-0.3.0.dist-info/entry_points.txt
bpcli-0.3.0.dist-info/top_level.txt
bpcli-0.3.0.dist-info/RECORD
