Metadata-Version: 2.1
Name: bpcli
Version: 0.3.0
Summary: Build apps with buildpacks and Dagger
Home-page: https://github.com/jfhovinne/bpcli
Author: jfhovinne
Author-email: bpcli@hovinne.com
License: MIT
Classifier: Programming Language :: Python :: 3
Classifier: License :: OSI Approved :: MIT License
Classifier: Operating System :: OS Independent
Classifier: Topic :: Software Development :: Build Tools
Requires-Python: >=3.10
License-File: LICENSE
Requires-Dist: asyncclick
Requires-Dist: dagger-io
